gmail_cleanup/__init__.py
gmail_cleanup/__main__.py
gmail_cleanup/cli.py
gmail_cleanup-0.1.2.dist-info/METADATA
gmail_cleanup-0.1.2.dist-info/WHEEL
gmail_cleanup-0.1.2.dist-info/entry_points.txt
gmail_cleanup-0.1.2.dist-info/top_level.txt
gmail_cleanup-0.1.2.dist-info/RECORD
