Metadata-Version: 2.4
Name: gmail-cleanup
Version: 0.1.2
Summary: Delete all unread Gmail threads via API
Author: Your Name
Requires-Dist: google-api-python-client
Requires-Dist: google-auth-httplib2
Requires-Dist: google-auth-oauthlib
Dynamic: author
Dynamic: requires-dist
Dynamic: summary
